LICENSE
MANIFEST.in
README.rst
requirements.txt
setup.py
1c_utilites.egg-info/PKG-INFO
1c_utilites.egg-info/SOURCES.txt
1c_utilites.egg-info/dependency_links.txt
1c_utilites.egg-info/entry_points.txt
1c_utilites.egg-info/requires.txt
1c_utilites.egg-info/top_level.txt
utilites_1c/__init__.py
utilites_1c/__main__.py
utilites_1c/manager.py
utilites_1c/settings.py
utilites_1c/utils.py
utilites_1c/backup/__init__.py
utilites_1c/backup/backends.py
utilites_1c/backup/base.py
utilites_1c/backup/file.py
utilites_1c/backup/postgres.py