Metadata-Version: 1.1
Name: 1c-utilites
Version: 0.1b0
Summary: Utilites for maintenance 1C services
Home-page: UNKNOWN
Author: Sergey Klyukov
Author-email: onegreyonewhite@mail.ru
License: AGPL+
Platform: UNKNOWN
Classifier: Operating System :: OS Independent
Classifier: Programming Language :: Python
Classifier: Programming Language :: Python :: 2
Classifier: Programming Language :: Python :: 2.7
Classifier: Programming Language :: Python :: 3
Classifier: Programming Language :: Python :: 3.4
Classifier: Programming Language :: Python :: 3.5
Classifier: Topic :: Utilities
